domain_stats/__init__.py
domain_stats/config.py
domain_stats/domain-loader.py
domain_stats/expiring_diskcache.py
domain_stats/freq.py
domain_stats/launch.py
domain_stats/network_io.py
domain_stats/rdap_query.py
domain_stats/server.py
domain_stats/settings.py
domain_stats/utils.py
domain_stats/data/domain_stats.service
domain_stats/data/domain_stats.zeek
domain_stats/data/elasticsearch.zeek.domain.pipeline
domain_stats/data/freqtable2018.freq
domain_stats/data/top1m.import
domain_stats-1.0.1.dist-info/COPYING
domain_stats-1.0.1.dist-info/METADATA
domain_stats-1.0.1.dist-info/WHEEL
domain_stats-1.0.1.dist-info/entry_points.txt
domain_stats-1.0.1.dist-info/top_level.txt
domain_stats-1.0.1.dist-info/RECORD
