Metadata-Version: 2.1
Name: domain-stats
Version: 1.0.1
Summary: Malicious Domain Detection base on domain creation and first contact
Home-page: https://github.com/markbaggett/domain_stats
Author: MarkBaggett
Author-email: lo127001@gmail.com
License: GNU General Public License v3 (GPLv3
Platform: UNKNOWN
Classifier: Programming Language :: Python :: 3
Classifier: License :: OSI Approved :: GNU General Public License v3 (GPLv3)
Classifier: Operating System :: OS Independent
Requires-Python: >=3.6
Requires-Dist: diskcache (>=5.1.0)
Requires-Dist: Flask (>=1.1.2)
Requires-Dist: gunicorn (>=20.0.4)
Requires-Dist: publicsuffixlist (>=0.7.6)
Requires-Dist: python-dateutil (>=2.8.1)
Requires-Dist: PyYAML (>=5.3.1)
Requires-Dist: rdap (>=1.1.0)
Requires-Dist: requests (==2.25.1)
